cube_utils-0.1.9.dist-info/METADATA
cube_utils-0.1.9.dist-info/WHEEL
cube_utils-0.1.9.dist-info/entry_points.txt
cube_utils-0.1.9.dist-info/licenses/LICENSE
cube_utils/__init__.py
cube_utils/query_parser.py
cube_utils/url_parser.py
cube_utils-0.1.9.dist-info/RECORD
