Metadata-Version: 2.1
Name: cube-utils
Version: 0.1.9
Summary: Python functions for Cube projects using cube.py config file.
Author-Email: Paco Valdez <paco.valdez@berkeley.edu>
License: MIT
Requires-Python: >=3.10
